anomsmith/__init__.py
anomsmith/objects/__init__.py
anomsmith/objects/validate.py
anomsmith/objects/views.py
anomsmith/objects/window.py
anomsmith/primitives/__init__.py
anomsmith/primitives/base.py
anomsmith/primitives/scaling.py
anomsmith/primitives/thresholding.py
anomsmith/primitives/detectors/__init__.py
anomsmith/primitives/detectors/_utils.py
anomsmith/primitives/detectors/change_point.py
anomsmith/primitives/detectors/ml.py
anomsmith/primitives/detectors/pca.py
anomsmith/primitives/scorers/__init__.py
anomsmith/primitives/scorers/robust_zscore.py
anomsmith/primitives/scorers/statistical.py
anomsmith/tasks/__init__.py
anomsmith/tasks/detect.py
anomsmith/tasks/helpers.py
anomsmith/workflows/__init__.py
anomsmith/workflows/detect.py
anomsmith/workflows/eval/__init__.py
anomsmith/workflows/eval/backtest.py
anomsmith/workflows/eval/metrics.py
anomsmith-0.0.2.dist-info/licenses/LICENSE
docs/conf.py
examples/basic_detect.py
examples/integration_timesmith.py
scripts/smoke.py
tests/__init__.py
tests/test_integration_timesmith.py
tests/test_objects_validate.py
tests/test_primitives_scaling.py
tests/test_primitives_thresholding.py
tests/test_workflows.py
tests/test_workflows_eval.py
anomsmith-0.0.2.dist-info/METADATA
anomsmith-0.0.2.dist-info/WHEEL
anomsmith-0.0.2.dist-info/entry_points.txt
anomsmith-0.0.2.dist-info/top_level.txt
anomsmith-0.0.2.dist-info/RECORD
