Metadata-Version: 2.4
Name: anomsmith
Version: 0.0.2
Summary: A strict 4-layer architecture for anomaly detection
Author-email: "Kyle T. Jones" <kyletjones@gmail.com>
Maintainer-email: "Kyle T. Jones" <kyletjones@gmail.com>
License-Expression: MIT
Project-URL: Homepage, https://github.com/kylejones200/anomsmith
Project-URL: Documentation, https://anomsmith.readthedocs.io/
Project-URL: Repository, https://github.com/kylejones200/anomsmith
Project-URL: Bug Tracker, https://github.com/kylejones200/anomsmith/issues
Project-URL: Changelog, https://github.com/kylejones200/anomsmith/blob/main/CHANGELOG.md
Requires-Python: >=3.9
License-File: LICENSE
Requires-Dist: numpy>=1.20.0
Requires-Dist: pandas>=1.3.0
Requires-Dist: scikit-learn>=1.0.0
Requires-Dist: timesmith<1.0.0,>=0.1.0
Provides-Extra: dev
Requires-Dist: pytest>=7.0; extra == "dev"
Requires-Dist: ruff>=0.1.0; extra == "dev"
Provides-Extra: deep
Requires-Dist: tensorflow>=2.8.0; extra == "deep"
Requires-Dist: torch>=1.11.0; extra == "deep"
Provides-Extra: wavelet
Requires-Dist: PyWavelets>=1.3.0; extra == "wavelet"
Provides-Extra: plots
Requires-Dist: plotsmith>=0.1.0; extra == "plots"
Provides-Extra: all
Requires-Dist: anomsmith[deep,plots,wavelet]; extra == "all"
Dynamic: license-file
